wy_qcos/__init__.py
wy_qcos/api_server.py
wy_qcos/server.py
wy_qcos/api/__init__.py
wy_qcos/api/fastapi_server.py
wy_qcos/api/isaq/__init__.py
wy_qcos/api/posiq/__init__.py
wy_qcos/api/posiq/routes_jsonrpc/__init__.py
wy_qcos/api/posiq/routes_jsonrpc/device.py
wy_qcos/api/posiq/routes_jsonrpc/driver.py
wy_qcos/api/posiq/routes_jsonrpc/errors.py
wy_qcos/api/posiq/routes_jsonrpc/job.py
wy_qcos/api/posiq/routes_jsonrpc/routes.py
wy_qcos/api/posiq/routes_jsonrpc/system.py
wy_qcos/api/posiq/routes_jsonrpc/transpiler.py
wy_qcos/api/posiq/routes_jsonrpc/version.py
wy_qcos/api/posiq/routes_jsonrpc/dependencies/__init__.py
wy_qcos/api/posiq/routes_jsonrpc/dependencies/authentication.py
wy_qcos/api/schemas/__init__.py
wy_qcos/api/schemas/device.py
wy_qcos/api/schemas/driver.py
wy_qcos/api/schemas/job.py
wy_qcos/api/schemas/system.py
wy_qcos/api/schemas/transpiler.py
wy_qcos/api/schemas/version.py
wy_qcos/common/__init__.py
wy_qcos/common/args_schema.py
wy_qcos/common/config.py
wy_qcos/common/constant.py
wy_qcos/common/errors.py
wy_qcos/common/library.py
wy_qcos/common/qcos_version.py
wy_qcos/drivers/__init__.py
wy_qcos/drivers/device.py
wy_qcos/drivers/device_manager.py
wy_qcos/drivers/driver_base.py
wy_qcos/drivers/driver_errors.py
wy_qcos/drivers/driver_manager.py
wy_qcos/drivers/driver_qubo_base.py
wy_qcos/drivers/driver_wuyue_base.py
wy_qcos/drivers/cascoldatom/__init__.py
wy_qcos/drivers/cascoldatom/driver_hanyuan1.py
wy_qcos/drivers/cascoldatom/driver_wuyue_hanyuan1.py
wy_qcos/drivers/dummy/__init__.py
wy_qcos/drivers/dummy/driver_dummy.py
wy_qcos/drivers/qboson/__init__.py
wy_qcos/drivers/qboson/driver_tiangong100.py
wy_qcos/drivers/qboson/driver_tiangong1000_v2.py
wy_qcos/drivers/qboson/driver_tiangong100_v2.py
wy_qcos/drivers/qboson/driver_tiangong550_v2.py
wy_qcos/drivers/qboson/driver_tiangong_base.py
wy_qcos/drivers/qiskit/__init__.py
wy_qcos/drivers/qiskit/driver_qiskit_aer_sim.py
wy_qcos/drivers/qiskit/driver_qiskit_qasm_sim.py
wy_qcos/drivers/qutip/__init__.py
wy_qcos-1.0.1.dist-info/licenses/AUTHORS
wy_qcos-1.0.1.dist-info/licenses/LICENSE
wy_qcos-1.0.1.dist-info/METADATA
wy_qcos-1.0.1.dist-info/WHEEL
wy_qcos-1.0.1.dist-info/entry_points.txt
wy_qcos-1.0.1.dist-info/top_level.txt
wy_qcos-1.0.1.dist-info/RECORD
