Metadata-Version: 2.4
Name: wy-qcos
Version: 1.0.1
Summary: QCOS (Quantum Computing Operating System)
Author-email: Zhao Yi <zhaoyi_yewu@cmss.chinamobile.com>, Ji Dalong <jidalong_yewu@cmss.chinamobile.com>, Xu Dong <xudong_yewu@cmss.chinamobile.com>, Wu Fangwei <wufangwei_yewu@cmss.chinamobile.com>, Guo Zhufeng <guozhufeng_yewu@cmss.chinamobile.com>, Liu Zhifeng <liuzhifeng_yewu@cmss.chinamobile.com>, Zhou Yunxiao <zhouyunxiao_yewu@cmss.chinamobile.com>, Ye Zhiwei <yezhiwei_yewu@cmss.chinamobile.com>, Huang Yachao <huangyachao_yewu@cmss.chinamobile.com>, Wang Jujun <wangjujun_yewu@cmss.chinamob
License:                      木兰宽松许可证, 第2版
Project-URL: Homepage, https://gitee.com/OpenWuYue/qcos
Project-URL: Documentation, https://qcos.readthedocs.io
Project-URL: Changelog, https://gitee.com/OpenWuYue/qcos/blob/develop/CHANGELOG.md
Project-URL: Issue Tracker, https://gitee.com/OpenWuYue/qcos/issues
Project-URL: Source, https://gitee.com/OpenWuYue/qcos
Keywords: qcos,quantum,operating,system
Classifier: Development Status :: 4 - Beta
Classifier: Environment :: Console
Classifier: Natural Language :: English
Classifier: Operating System :: POSIX
Classifier: Operating System :: POSIX :: Linux
Classifier: Programming Language :: Python
Classifier: Programming Language :: Python :: 3
Classifier: Programming Language :: Python :: 3.10
Classifier: Programming Language :: Python :: 3.11
Classifier: Programming Language :: Python :: Implementation :: CPython
Requires-Python: <3.14,>=3.11
License-File: LICENSE
License-File: AUTHORS
Requires-Dist: aiohttp==3.12.13
Requires-Dist: alembic==1.16.3
Requires-Dist: annotated-types==0.7.0
Requires-Dist: anyio==4.9.0
Requires-Dist: argcomplete==3.6.2
Requires-Dist: click==8.1.8
Requires-Dist: cliff==4.10.0
Requires-Dist: cryptography==45.0.7
Requires-Dist: fastapi==0.122.1
Requires-Dist: fastapi-jsonrpc==3.4.2
Requires-Dist: h11==0.16.0
Requires-Dist: httpcore==1.0.9
Requires-Dist: httpx==0.28.1
Requires-Dist: idna==3.10
Requires-Dist: jsonrpcclient==4.0.3
Requires-Dist: loguru==0.7.3
Requires-Dist: matplotlib==3.9.2
Requires-Dist: mqt.qcec==3.3.0
Requires-Dist: networkx==3.3
Requires-Dist: numexpr==2.14.1
Requires-Dist: numpy==1.26.4
Requires-Dist: opentelemetry-api==1.39.1
Requires-Dist: pallets-sphinx-themes==2.3.0
Requires-Dist: ply==3.11
Requires-Dist: poetry==2.1.3
Requires-Dist: prefect==3.6.9; sys_platform == "linux"
Requires-Dist: pulp==3.2.2
Requires-Dist: pydantic==2.11.5
Requires-Dist: pydantic_core==2.33.2
Requires-Dist: pydocket==0.16.3
Requires-Dist: pytest==8.4.1
Requires-Dist: pytest-cov==6.2.1
Requires-Dist: qiskit==2.1.1
Requires-Dist: qiskit_aer==0.17.1
Requires-Dist: requests==2.32.5
Requires-Dist: rustworkx==0.16.0
Requires-Dist: schema==0.7.7
Requires-Dist: sniffio==1.3.1
Requires-Dist: starlette==0.50.0
Requires-Dist: tomlkit==0.13.3
Requires-Dist: typing-inspection==0.4.1
Requires-Dist: typing_extensions==4.15.0
Requires-Dist: uvicorn==0.34.2
Requires-Dist: wheel==0.45.1
Requires-Dist: bandit>=1.8.6
Requires-Dist: flake8>=7.3.0
Requires-Dist: mypy==1.16.1
Requires-Dist: pytest>=8.4.1
Requires-Dist: pytest-cov>=6.2.1
Requires-Dist: ruff==0.12.3
Requires-Dist: sphinx==8.1.3
Requires-Dist: sphinx-rtd-theme==3.0.2
Requires-Dist: sphinxcontrib-napoleon==0.7
Requires-Dist: tabulate==0.9.0
Requires-Dist: tomli==2.2.1
Requires-Dist: tox==4.8.0
Dynamic: license-file
